dzdbgport.py
dzdbgport-0.3.0.dist-info/METADATA
dzdbgport-0.3.0.dist-info/WHEEL
dzdbgport-0.3.0.dist-info/RECORD
