Metadata-Version: 2.1
Name: dzdbgport
Version: 0.3.0
Summary: Unofficial DayZ debugging tool for VSCode and development package in Python.
Author: Yuval
Author-email: yuvalino@gmail.com
Requires-Python: >=3.12,<3.14
Classifier: Programming Language :: Python :: 3
Classifier: Programming Language :: Python :: 3.12
Classifier: Programming Language :: Python :: 3.13
Requires-Dist: prompt-toolkit (>=3.0.51,<4.0.0)
Requires-Dist: websockets (>=15.0.1,<16.0.0)
Project-URL: Github, https://github.com/yuvalino/dzdbgport
